[
	{
		"title": "main - help",
		"tag": "main",
		"text": "ky!Help <optional tag> || Shows all availible help commands. Following the command with a tag prunes the embed for all commands that fit the tag."
	},{
		"title": "main - about",
		"tag": "main",
		"text": "ky!about || Displays Kanade Bot about embed"
	},{
		"title": "arcade - ealinks",
		"tag": "arcade",
		"text": "ky!ealinks || Displays various important e-amusement links"
	},{
		"title": "iidx - exscore",
		"tag": "iidx",
		"text": "ky!exscore <Total Notes> || Calculates the EXSCORE amount necesary to get MAX, AAA, AA, or A from a songs total notes."
	},{
		"title": "iidx - iidxdansp",
		"tag": "iidx",
		"text": "ky!iidxdansp <class-section> || displays IIDX class courses per section. (SP) Valid Arguments: kyu, dan, and den"
	},{
		"title": "iidx - iidxdandp",
		"tag": "iidx",
		"text": "ky!iidxdandp <class-section> || displays IIDX class courses per section. (DP) Valid Arguments: kyu, dan, and den"
	},{
		"title": "sdvx - sdvxdan",
		"tag": "sdvx",
		"text": "ky!sdvxdan <skill-level> || Displays SDVX SKILL ANALYZER courses per skill level. Valid Arguments: 1 - 11 and inf"
	},{
		"title": "sdvx - vf",
		"tag": "sdvx",
		"text": "ky!vf <First 4 of score> <PUC, UC, etc.> <difficulty> || Determines Volforce by user provided values."
	},{
		"title": "arcade - remywiki",
		"tag": "arcade",
		"text": "ky!remywiki <search term> || Searches RemyWiki and links it to channel used"
	},{
		"title": "arcade - playsleft",
		"tag": "arcade",
		"text": "ky!playsleft <number of credits> || Sends how many plays left you have on 8 credit rhythm game based on user input."
	},{
		"title": "sdvx - sdvxtier",
		"tag": "sdvx",
		"text": "ky!sdvxtier || Sends link for SDVX clear tierlist"
	},{
		"title": "main - gacha",
		"tag": "main",
		"text": "ky!gacha || Sends a random response"
	},{
		"title": "arcade - verify",
		"tag": "arcade",
		"text": "ky!verify <Attached Image>|| Submits rhythm game score for role verification."
	},{
		"title": "admin - boost",
		"tag": "admin",
		"text": "ky!boost || Creates a txt file listing all current server boosters"
	},{
		"title": "admin - bonk",
		"tag": "admin",
		"text": "ky!bonk <user-mention> || Sends mentioned user to horny jail"
	},{
		"title": "admin - unbonk",
		"tag": "admin",
		"text": "ky!unbonk <user-mention> || Removes mentioned user to horny jail"
	},{
		"title": "admin - copy",
		"tag": "admin",
		"text": "ky!copy || counts every message sent in every channel (Lolzep Only)"
	},{
		"title": "admin - memberupdate",
		"tag": "admin",
		"text": "ky!memberupdate || Updates the member count."
	},{
		"title": "admin - forceabout",
		"tag": "admin",
		"text": "kyt!forceabout || Forces public facing ky!about while in debug mode."
	},{
		"title": "admin - noresponse",
		"tag": "admin",
		"text": "ky!noresponse || Disables bot responses in all channels for 30 mins."
	},{
		"title": "admin - restart",
		"tag": "admin",
		"text": "ky!restart || Restarts Kanade Bot"
	},{
		"title": "admin - gitpull",
		"tag": "admin",
		"text": "ky!gitpull || pulls latest git commit"
	},{
		"title": "main - certain messages",
		"tag": "main",
		"text": "imminent funni"
	}
]